otcextensions/__init__.py
otcextensions/_hacking.py
otcextensions/i18n.py
otcextensions/common/__init__.py
otcextensions/common/agency_auth.py
otcextensions/common/cli_utils.py
otcextensions/common/errors.py
otcextensions/common/exc.py
otcextensions/common/format.py
otcextensions/common/sdk_utils.py
otcextensions/common/utils.py
otcextensions/osclient/__init__.py
otcextensions/osclient/anti_ddos/__init__.py
otcextensions/osclient/anti_ddos/client.py
otcextensions/osclient/anti_ddos/v1/__init__.py
otcextensions/osclient/anti_ddos/v1/config.py
otcextensions/osclient/anti_ddos/v1/floating_ip.py
otcextensions/osclient/anti_ddos/v1/status.py
otcextensions/osclient/auto_scaling/__init__.py
otcextensions/osclient/auto_scaling/client.py
otcextensions/osclient/auto_scaling/v1/__init__.py
otcextensions/osclient/auto_scaling/v1/activity.py
otcextensions/osclient/auto_scaling/v1/config.py
otcextensions/osclient/auto_scaling/v1/group.py
otcextensions/osclient/auto_scaling/v1/instance.py
otcextensions/osclient/auto_scaling/v1/policy.py
otcextensions/osclient/auto_scaling/v1/quota.py
otcextensions/osclient/cbr/__init__.py
otcextensions/osclient/cbr/client.py
otcextensions/osclient/cbr/v3/__init__.py
otcextensions/osclient/cbr/v3/backup.py
otcextensions/osclient/cbr/v3/checkpoint.py
otcextensions/osclient/cbr/v3/member.py
otcextensions/osclient/cbr/v3/policy.py
otcextensions/osclient/cbr/v3/task.py
otcextensions/osclient/cbr/v3/vault.py
otcextensions/osclient/cce/__init__.py
otcextensions/osclient/cce/client.py
otcextensions/osclient/cce/v1/__init__.py
otcextensions/osclient/cce/v1/cluster.py
otcextensions/osclient/cce/v1/cluster_node.py
otcextensions/osclient/cce/v2/__init__.py
otcextensions/osclient/cce/v2/cluster.py
otcextensions/osclient/cce/v2/cluster_certificate.py
otcextensions/osclient/cce/v2/cluster_node.py
otcextensions/osclient/cce/v2/node_pool.py
otcextensions/osclient/ces/__init__.py
otcextensions/osclient/ces/client.py
otcextensions/osclient/ces/v1/__init__.py
otcextensions-0.32.29.dist-info/licenses/AUTHORS
otcextensions-0.32.29.dist-info/licenses/LICENSE
otcextensions-0.32.29.dist-info/METADATA
otcextensions-0.32.29.dist-info/WHEEL
otcextensions-0.32.29.dist-info/entry_points.txt
otcextensions-0.32.29.dist-info/pbr.json
otcextensions-0.32.29.dist-info/top_level.txt
otcextensions-0.32.29.dist-info/RECORD
