Metadata-Version: 2.4
Name: otcextensions
Version: 0.32.29
Summary: Open Telekom Cloud specific extensions for the OpenStack Client CLI and OpenStack SDK
Home-page: http://python-otcextensions.readthedocs.io/
Author: Artem Goncharov
Author-email: artem.goncharov@gmail.com
Keywords: OpenStack, openstackclient, openstacksdk, Open Telekom Cloud, otc, T-Systems, Telekom
Classifier: Environment :: OpenStack
Classifier: Intended Audience :: Information Technology
Classifier: Intended Audience :: System Administrators
Classifier: License :: OSI Approved :: Apache Software License
Classifier: Operating System :: POSIX :: Linux
Classifier: Programming Language :: Python
Classifier: Programming Language :: Python :: 2
Classifier: Programming Language :: Python :: 2.7
Classifier: Programming Language :: Python :: 3
Classifier: Programming Language :: Python :: 3.6
Classifier: Programming Language :: Python :: 3.7
License-File: LICENSE
License-File: AUTHORS
Requires-Dist: openstacksdk>=0.100.0
Requires-Dist: oslo.i18n>3.15.3
Requires-Dist: python-novaclient>=18.9.0
Dynamic: author
Dynamic: author-email
Dynamic: classifier
Dynamic: description
Dynamic: home-page
Dynamic: keywords
Dynamic: license-file
Dynamic: requires-dist
Dynamic: summary
